[
null,
{"id":1,"autoRemovalTiming":0,"chanceByDamage":100,"iconIndex":688,"maxTurns":1,"message1":"%1 has fallen!","message2":"%1 is slain!","message3":"","message4":"%1 revives!","minTurns":1,"motion":3,"name":"Dead","note":"State #1 will be added when HP hits 0.","overlay":0,"priority":100,"releaseByDamage":false,"removeAtBattleEnd":false,"removeByDamage":false,"removeByRestriction":false,"removeByWalking":false,"restriction":4,"stepsToRemove":100,"traits":[{"code":23,"dataId":9,"value":0}],"messageType":1},
{"id":2,"autoRemovalTiming":2,"chanceByDamage":100,"iconIndex":0,"maxTurns":1,"message1":"","message2":"","message3":"","message4":"","minTurns":1,"motion":0,"name":"Guard","note":"","overlay":0,"priority":0,"removeAtBattleEnd":true,"removeByDamage":false,"removeByRestriction":true,"removeByWalking":false,"restriction":0,"stepsToRemove":100,"traits":[{"code":62,"dataId":1,"value":0}],"messageType":1},
{"id":3,"autoRemovalTiming":0,"chanceByDamage":100,"iconIndex":0,"maxTurns":1,"message1":"","message2":"","message3":"","message4":"","minTurns":1,"motion":0,"name":"Immortal","note":"","overlay":0,"priority":0,"removeAtBattleEnd":true,"removeByDamage":false,"removeByRestriction":false,"removeByWalking":false,"restriction":0,"stepsToRemove":100,"traits":[{"code":14,"dataId":1,"value":0}],"messageType":1},
{"id":4,"autoRemovalTiming":0,"chanceByDamage":100,"iconIndex":689,"maxTurns":1,"message1":"%1 is poisoned!","message2":"%1 is poisoned!","message3":"","message4":"%1 is no longer poisoned!","minTurns":1,"motion":1,"overlay":1,"name":"Poison","note":"","priority":50,"releaseByDamage":false,"removeAtBattleEnd":false,"removeByDamage":false,"removeByRestriction":false,"removeByWalking":false,"restriction":0,"stepsToRemove":100,"traits":[{"code":22,"dataId":7,"value":-0.1}],"messageType":1},
{"id":5,"autoRemovalTiming":1,"chanceByDamage":100,"iconIndex":690,"maxTurns":5,"message1":"%1 is blinded!","message2":"%1 is blinded!","message3":"","message4":"%1 is no longer blinded!","minTurns":3,"motion":1,"name":"Blind","note":"","overlay":2,"priority":60,"releaseByDamage":false,"removeAtBattleEnd":false,"removeByDamage":false,"removeByRestriction":false,"removeByWalking":false,"restriction":0,"stepsToRemove":100,"traits":[{"code":22,"dataId":0,"value":-0.5}],"messageType":1},
{"id":6,"autoRemovalTiming":1,"chanceByDamage":100,"iconIndex":691,"maxTurns":5,"message1":"%1 is silenced!","message2":"%1 is silenced!","message3":"","message4":"%1 is no longer silenced!","minTurns":3,"motion":1,"name":"Silence","note":"","overlay":3,"priority":65,"releaseByDamage":false,"removeAtBattleEnd":false,"removeByDamage":false,"removeByRestriction":false,"removeByWalking":false,"restriction":0,"stepsToRemove":100,"traits":[{"code":42,"dataId":1,"value":0}],"messageType":1},
{"id":7,"autoRemovalTiming":1,"chanceByDamage":50,"iconIndex":692,"maxTurns":4,"message1":"%1 is enraged!","message2":"%1 is enraged!","message3":"","message4":"%1 is no longer enraged!","minTurns":2,"motion":1,"name":"Rage","note":"","overlay":4,"priority":70,"releaseByDamage":false,"removeAtBattleEnd":true,"removeByDamage":true,"removeByRestriction":false,"removeByWalking":false,"restriction":1,"stepsToRemove":100,"traits":[],"messageType":1},
{"id":8,"autoRemovalTiming":1,"chanceByDamage":50,"iconIndex":693,"maxTurns":4,"message1":"%1 is confused!","message2":"%1 is confused!","message3":"","message4":"%1 is no longer confused!","minTurns":2,"motion":1,"name":"Confusion","note":"","overlay":5,"priority":75,"releaseByDamage":false,"removeAtBattleEnd":true,"removeByDamage":true,"removeByRestriction":false,"removeByWalking":false,"restriction":2,"stepsToRemove":100,"traits":[],"messageType":1},
{"id":9,"autoRemovalTiming":1,"chanceByDamage":50,"iconIndex":694,"maxTurns":4,"message1":"%1 is charmed!","message2":"%1 is charmed!","message3":"","message4":"%1 is no longer charmed!","minTurns":2,"motion":1,"name":"Charm","note":"","overlay":6,"priority":80,"releaseByDamage":false,"removeAtBattleEnd":true,"removeByDamage":true,"removeByRestriction":false,"removeByWalking":false,"restriction":3,"stepsToRemove":100,"traits":[],"messageType":1},
{"id":10,"autoRemovalTiming":1,"chanceByDamage":100,"iconIndex":695,"maxTurns":5,"message1":"%1 falls asleep!","message2":"%1 falls asleep!","message3":"%1 is sleeping.","message4":"%1 wakes up!","minTurns":3,"motion":2,"name":"Sleep","note":"","overlay":7,"priority":90,"releaseByDamage":true,"removeAtBattleEnd":true,"removeByDamage":true,"removeByRestriction":false,"removeByWalking":false,"restriction":4,"stepsToRemove":100,"traits":[{"code":22,"dataId":1,"value":-1}],"messageType":1},
{"id":11,"autoRemovalTiming":0,"chanceByDamage":100,"traits":[],"iconIndex":0,"maxTurns":1,"message1":"","message2":"","message3":"","message4":"","minTurns":1,"motion":0,"name":"","note":"","overlay":0,"priority":50,"removeAtBattleEnd":false,"removeByDamage":false,"removeByRestriction":false,"removeByWalking":false,"restriction":0,"stepsToRemove":100,"messageType":1},
{"id":12,"autoRemovalTiming":2,"chanceByDamage":100,"traits":[{"code":22,"dataId":1,"value":-1}],"iconIndex":696,"maxTurns":3,"message1":"%1 is paralyzed and can’t move!","message2":"%1 is paralyzed!","message3":"%1 is paralyzed and can’t move!","message4":"%1 is no longer paralyzed!","minTurns":3,"motion":2,"name":"Paralysis","note":"","overlay":8,"priority":95,"removeAtBattleEnd":true,"removeByDamage":false,"removeByRestriction":false,"removeByWalking":false,"restriction":4,"stepsToRemove":100,"messageType":1},
{"id":13,"autoRemovalTiming":2,"chanceByDamage":100,"traits":[{"code":22,"dataId":1,"value":-1}],"iconIndex":697,"maxTurns":2,"message1":"%1 lost balance!","message2":"%1 lost balance!","message3":"%1 is still off-balance...","message4":"%1 has regained balance!","minTurns":1,"motion":1,"name":"Stun","note":"","overlay":10,"priority":90,"removeAtBattleEnd":true,"removeByDamage":false,"removeByRestriction":false,"removeByWalking":false,"restriction":4,"stepsToRemove":100,"messageType":1},
{"id":14,"autoRemovalTiming":0,"chanceByDamage":100,"traits":[],"iconIndex":0,"maxTurns":1,"message1":"","message2":"","message3":"","message4":"","minTurns":1,"motion":0,"name":"","note":"","overlay":0,"priority":50,"removeAtBattleEnd":false,"removeByDamage":false,"removeByRestriction":false,"removeByWalking":false,"restriction":0,"stepsToRemove":100,"messageType":1},
{"id":15,"autoRemovalTiming":0,"chanceByDamage":100,"traits":[],"iconIndex":0,"maxTurns":1,"message1":"","message2":"","message3":"","message4":"","messageType":1,"minTurns":1,"motion":0,"name":"---- Custom ----","note":"","overlay":0,"priority":50,"removeAtBattleEnd":false,"removeByDamage":false,"removeByRestriction":false,"removeByWalking":false,"restriction":0,"stepsToRemove":100},
{"id":16,"autoRemovalTiming":1,"chanceByDamage":100,"traits":[{"code":23,"dataId":6,"value":1.1},{"code":22,"dataId":1,"value":-0.15},{"code":22,"dataId":3,"value":-0.15}],"iconIndex":672,"maxTurns":4,"message1":"%1 is marked as prey!","message2":"%1 is marked as prey!","message3":"","message4":"%1 is no longer marked.","messageType":1,"minTurns":4,"motion":0,"name":"Marked","note":"","overlay":0,"priority":50,"removeAtBattleEnd":true,"removeByDamage":false,"removeByRestriction":false,"removeByWalking":false,"restriction":0,"stepsToRemove":100},
{"id":17,"autoRemovalTiming":1,"chanceByDamage":100,"traits":[{"code":21,"dataId":3,"value":0.7},{"code":23,"dataId":6,"value":1.1}],"iconIndex":673,"maxTurns":3,"message1":"%1's body weakens!","message2":"%1's body weakens!","message3":"","message4":"%1's strength returns.","messageType":1,"minTurns":3,"motion":0,"name":"Frailty","note":"","overlay":0,"priority":50,"removeAtBattleEnd":true,"removeByDamage":false,"removeByRestriction":false,"removeByWalking":false,"restriction":0,"stepsToRemove":100},
{"id":18,"autoRemovalTiming":1,"chanceByDamage":100,"traits":[{"code":21,"dataId":5,"value":0.7},{"code":23,"dataId":7,"value":1.1}],"iconIndex":674,"maxTurns":3,"message1":"%1's magic guard is exposed!","message2":"%1's magic guard is exposed!","message3":"","message4":"%1 is no longer exposed.","messageType":1,"minTurns":3,"motion":0,"name":"Exposed","note":"","overlay":0,"priority":50,"removeAtBattleEnd":true,"removeByDamage":false,"removeByRestriction":false,"removeByWalking":false,"restriction":0,"stepsToRemove":100},
{"id":19,"autoRemovalTiming":1,"chanceByDamage":100,"traits":[{"code":21,"dataId":6,"value":0.5},{"code":22,"dataId":1,"value":-0.2}],"iconIndex":675,"maxTurns":2,"message1":"%1 is pinned down!","message2":"%1 is pinned down!","message3":"","message4":"%1 breaks free!","messageType":1,"minTurns":2,"motion":1,"name":"Pinning","note":"","overlay":0,"priority":50,"removeAtBattleEnd":true,"removeByDamage":false,"removeByRestriction":false,"removeByWalking":false,"restriction":0,"stepsToRemove":100},
{"id":20,"autoRemovalTiming":2,"chanceByDamage":100,"traits":[{"code":22,"dataId":0,"value":0.25},{"code":22,"dataId":2,"value":0.15}],"iconIndex":676,"maxTurns":4,"message1":"%1 focuses their aim!","message2":"%1 focuses their aim!","message3":"","message4":"%1's focus fades.","messageType":1,"minTurns":4,"motion":0,"name":"Eagle Eye","note":"","overlay":0,"priority":50,"removeAtBattleEnd":true,"removeByDamage":false,"removeByRestriction":false,"removeByWalking":false,"restriction":0,"stepsToRemove":100},
{"id":21,"autoRemovalTiming":1,"chanceByDamage":100,"traits":[{"code":22,"dataId":0,"value":0.5},{"code":22,"dataId":2,"value":0.25}],"iconIndex":677,"maxTurns":2,"message1":"%1 prepares for the hunt!","message2":"%1 prepares for the hunt!","message3":"","message4":"%1's hunting focus fades.","messageType":1,"minTurns":2,"motion":0,"name":"Hunter's Focus","note":"","overlay":0,"priority":50,"removeAtBattleEnd":true,"removeByDamage":false,"removeByRestriction":false,"removeByWalking":false,"restriction":0,"stepsToRemove":100},
{"id":22,"autoRemovalTiming":2,"chanceByDamage":100,"traits":[{"code":21,"dataId":2,"value":1.25},{"code":23,"dataId":0,"value":1.5}],"iconIndex":678,"maxTurns":4,"message1":"%1 lets out a war cry!","message2":"%1 lets out a war cry!","message3":"","message4":"%1's war cry fades.","messageType":1,"minTurns":4,"motion":0,"name":"War Cry","note":"","overlay":0,"priority":50,"removeAtBattleEnd":true,"removeByDamage":false,"removeByRestriction":false,"removeByWalking":false,"restriction":0,"stepsToRemove":100},
{"id":23,"autoRemovalTiming":2,"chanceByDamage":100,"traits":[{"code":21,"dataId":2,"value":1.15},{"code":22,"dataId":2,"value":0.1},{"code":23,"dataId":5,"value":1.5}],"iconIndex":679,"maxTurns":4,"message1":"%1 enters a battle trance!","message2":"%1 enters a battle trance!","message3":"","message4":"%1's battle trance fades.","messageType":1,"minTurns":4,"motion":0,"name":"Battle Trance","note":"","overlay":0,"priority":50,"removeAtBattleEnd":true,"removeByDamage":false,"removeByRestriction":false,"removeByWalking":false,"restriction":0,"stepsToRemove":100},
{"id":24,"autoRemovalTiming":2,"chanceByDamage":100,"traits":[{"code":23,"dataId":6,"value":0.8}],"iconIndex":680,"maxTurns":4,"message1":"%1 is protected!","message2":"%1 is protected!","message3":"","message4":"%1 is no longer protected.","messageType":1,"minTurns":4,"motion":0,"name":"Protect","note":"","overlay":0,"priority":50,"removeAtBattleEnd":true,"removeByDamage":false,"removeByRestriction":false,"removeByWalking":false,"restriction":0,"stepsToRemove":100},
{"id":25,"autoRemovalTiming":2,"chanceByDamage":100,"traits":[{"code":23,"dataId":7,"value":0.8}],"iconIndex":681,"maxTurns":4,"message1":"%1 is shelled!","message2":"%1 is shelled!","message3":"","message4":"%1's shell fades.","messageType":1,"minTurns":4,"motion":0,"name":"Shell","note":"","overlay":0,"priority":50,"removeAtBattleEnd":true,"removeByDamage":false,"removeByRestriction":false,"removeByWalking":false,"restriction":0,"stepsToRemove":100},
{"id":26,"autoRemovalTiming":2,"chanceByDamage":100,"traits":[{"code":22,"dataId":7,"value":0.12},{"code":23,"dataId":2,"value":1.25},{"code":14,"dataId":28,"value":1}],"iconIndex":682,"maxTurns":4,"message1":"%1 is renewed!","message2":"%1 is renewed!","message3":"","message4":"%1 is no longer renewed.","messageType":1,"minTurns":4,"motion":0,"name":"Renew","note":"","overlay":0,"priority":50,"removeAtBattleEnd":true,"removeByDamage":false,"removeByRestriction":false,"removeByWalking":false,"restriction":0,"stepsToRemove":100},
{"id":27,"autoRemovalTiming":2,"chanceByDamage":100,"traits":[{"code":23,"dataId":6,"value":0.9},{"code":23,"dataId":7,"value":0.9},{"code":22,"dataId":7,"value":0.04},{"code":23,"dataId":2,"value":1.1}],"iconIndex":683,"maxTurns":3,"message1":"%1 is sheltered by sanctuary!","message2":"%1 is sheltered by sanctuary!","message3":"","message4":"%1 leaves sanctuary's protection.","messageType":1,"minTurns":3,"motion":0,"name":"Sanctuary","note":"","overlay":0,"priority":50,"removeAtBattleEnd":true,"removeByDamage":false,"removeByRestriction":false,"removeByWalking":false,"restriction":0,"stepsToRemove":100},
{"id":28,"autoRemovalTiming":2,"chanceByDamage":100,"traits":[{"code":22,"dataId":7,"value":0.06}],"iconIndex":684,"maxTurns":5,"message1":"%1 begins regenerating!","message2":"%1 begins regenerating!","message3":"","message4":"%1 stops regenerating.","messageType":1,"minTurns":5,"motion":0,"name":"Regen","note":"","overlay":0,"priority":50,"removeAtBattleEnd":true,"removeByDamage":false,"removeByRestriction":false,"removeByWalking":false,"restriction":0,"stepsToRemove":100},
{"id":29,"autoRemovalTiming":2,"chanceByDamage":100,"traits":[{"code":23,"dataId":0,"value":3.5},{"code":23,"dataId":1,"value":1.5},{"code":23,"dataId":6,"value":0.9}],"iconIndex":698,"maxTurns":4,"message1":"%1 holds the line!","message2":"","message3":"","message4":"%1 lowers their guard.","messageType":1,"minTurns":4,"motion":0,"name":"Knight's Guard","note":"","overlay":0,"priority":50,"removeAtBattleEnd":true,"removeByDamage":false,"removeByRestriction":false,"removeByWalking":false,"restriction":0,"stepsToRemove":100},
{"id":30,"autoRemovalTiming":2,"chanceByDamage":100,"traits":[{"code":23,"dataId":6,"value":0.85},{"code":23,"dataId":7,"value":0.9}],"iconIndex":699,"maxTurns":4,"message1":"%1 is protected by a guardian's oath!","message2":"","message3":"","message4":"%1 is no longer oathguarded.","messageType":1,"minTurns":4,"motion":0,"name":"Oathguard","note":"","overlay":0,"priority":50,"removeAtBattleEnd":true,"removeByDamage":false,"removeByRestriction":false,"removeByWalking":false,"restriction":0,"stepsToRemove":100},
{"id":31,"autoRemovalTiming":2,"chanceByDamage":100,"traits":[{"code":62,"dataId":2,"value":1},{"code":23,"dataId":0,"value":3},{"code":23,"dataId":1,"value":1.5},{"code":23,"dataId":6,"value":0.9},{"code":23,"dataId":7,"value":0.95}],"iconIndex":700,"maxTurns":3,"message1":"%1 steps forward to interpose!","message2":"","message3":"","message4":"%1 lowers their guard.","messageType":1,"minTurns":3,"motion":0,"name":"Interpose","note":"","overlay":0,"priority":50,"removeAtBattleEnd":true,"removeByDamage":false,"removeByRestriction":false,"removeByWalking":false,"restriction":0,"stepsToRemove":100},
{"id":32,"autoRemovalTiming":2,"chanceByDamage":100,"traits":[{"code":23,"dataId":6,"value":0.9},{"code":23,"dataId":1,"value":1.2}],"iconIndex":701,"maxTurns":3,"message1":"%1 is shielded by the wall!","message2":"","message3":"","message4":"%1 is no longer shielded.","messageType":1,"minTurns":3,"motion":0,"name":"Shield Wall","note":"","overlay":0,"priority":50,"removeAtBattleEnd":true,"removeByDamage":false,"removeByRestriction":false,"removeByWalking":false,"restriction":0,"stepsToRemove":100},
{"id":33,"autoRemovalTiming":2,"chanceByDamage":100,"traits":[{"code":23,"dataId":6,"value":0.85},{"code":23,"dataId":7,"value":0.9}],"iconIndex":702,"maxTurns":3,"message1":"%1 is protected by the king's aegis!","message2":"","message3":"","message4":"%1 is no longer protected by the aegis.","messageType":1,"minTurns":3,"motion":0,"name":"King's Aegis","note":"","overlay":0,"priority":50,"removeAtBattleEnd":true,"removeByDamage":false,"removeByRestriction":false,"removeByWalking":false,"restriction":0,"stepsToRemove":100},
{"id":34,"autoRemovalTiming":2,"chanceByDamage":100,"traits":[{"code":23,"dataId":0,"value":5},{"code":23,"dataId":1,"value":2},{"code":23,"dataId":6,"value":0.75},{"code":23,"dataId":7,"value":0.85},{"code":22,"dataId":7,"value":0.05}],"iconIndex":703,"maxTurns":4,"message1":"%1 becomes the last bastion!","message2":"","message3":"","message4":"%1's last bastion fades.","messageType":1,"minTurns":4,"motion":0,"name":"Last Bastion","note":"","overlay":0,"priority":50,"removeAtBattleEnd":true,"removeByDamage":false,"removeByRestriction":false,"removeByWalking":false,"restriction":0,"stepsToRemove":100},
{"id":35,"autoRemovalTiming":0,"chanceByDamage":100,"traits":[{"code":22,"dataId":1,"value":1},{"code":22,"dataId":4,"value":1},{"code":23,"dataId":0,"value":0}],"iconIndex":0,"maxTurns":1,"message1":"","message2":"%1 launches into the air!","message3":"","message4":"%1 comes crashing down in flames!","messageType":1,"minTurns":1,"motion":0,"name":"Preparing Helljump","note":"<JS Accuracy as Target>\nrate = 0;\n</JS Accuracy as Target>","overlay":0,"priority":70,"removeAtBattleEnd":true,"removeByDamage":false,"removeByRestriction":false,"removeByWalking":false,"restriction":0,"stepsToRemove":100},
{"id":36,"autoRemovalTiming":0,"chanceByDamage":100,"traits":[],"iconIndex":0,"maxTurns":1,"message1":"","message2":"","message3":"","message4":"","messageType":1,"minTurns":1,"motion":0,"name":"","note":"","overlay":0,"priority":50,"removeAtBattleEnd":false,"removeByDamage":false,"removeByRestriction":false,"removeByWalking":false,"restriction":0,"stepsToRemove":100},
{"id":37,"autoRemovalTiming":0,"chanceByDamage":100,"traits":[],"iconIndex":0,"maxTurns":1,"message1":"","message2":"","message3":"","message4":"","messageType":1,"minTurns":1,"motion":0,"name":"","note":"","overlay":0,"priority":50,"removeAtBattleEnd":false,"removeByDamage":false,"removeByRestriction":false,"removeByWalking":false,"restriction":0,"stepsToRemove":100},
{"id":38,"autoRemovalTiming":0,"chanceByDamage":100,"traits":[],"iconIndex":0,"maxTurns":1,"message1":"","message2":"","message3":"","message4":"","messageType":1,"minTurns":1,"motion":0,"name":"","note":"","overlay":0,"priority":50,"removeAtBattleEnd":false,"removeByDamage":false,"removeByRestriction":false,"removeByWalking":false,"restriction":0,"stepsToRemove":100},
{"id":39,"autoRemovalTiming":0,"chanceByDamage":100,"traits":[],"iconIndex":0,"maxTurns":1,"message1":"","message2":"","message3":"","message4":"","messageType":1,"minTurns":1,"motion":0,"name":"","note":"","overlay":0,"priority":50,"removeAtBattleEnd":false,"removeByDamage":false,"removeByRestriction":false,"removeByWalking":false,"restriction":0,"stepsToRemove":100},
{"id":40,"autoRemovalTiming":0,"chanceByDamage":100,"traits":[],"iconIndex":0,"maxTurns":1,"message1":"","message2":"","message3":"","message4":"","messageType":1,"minTurns":1,"motion":0,"name":"","note":"","overlay":0,"priority":50,"removeAtBattleEnd":false,"removeByDamage":false,"removeByRestriction":false,"removeByWalking":false,"restriction":0,"stepsToRemove":100},
{"id":41,"autoRemovalTiming":0,"chanceByDamage":100,"traits":[],"iconIndex":0,"maxTurns":1,"message1":"","message2":"","message3":"","message4":"","messageType":1,"minTurns":1,"motion":0,"name":"","note":"","overlay":0,"priority":50,"removeAtBattleEnd":false,"removeByDamage":false,"removeByRestriction":false,"removeByWalking":false,"restriction":0,"stepsToRemove":100},
{"id":42,"autoRemovalTiming":0,"chanceByDamage":100,"traits":[],"iconIndex":0,"maxTurns":1,"message1":"","message2":"","message3":"","message4":"","messageType":1,"minTurns":1,"motion":0,"name":"","note":"","overlay":0,"priority":50,"removeAtBattleEnd":false,"removeByDamage":false,"removeByRestriction":false,"removeByWalking":false,"restriction":0,"stepsToRemove":100},
{"id":43,"autoRemovalTiming":0,"chanceByDamage":100,"traits":[],"iconIndex":0,"maxTurns":1,"message1":"","message2":"","message3":"","message4":"","messageType":1,"minTurns":1,"motion":0,"name":"","note":"","overlay":0,"priority":50,"removeAtBattleEnd":false,"removeByDamage":false,"removeByRestriction":false,"removeByWalking":false,"restriction":0,"stepsToRemove":100},
{"id":44,"autoRemovalTiming":0,"chanceByDamage":100,"traits":[],"iconIndex":0,"maxTurns":1,"message1":"","message2":"","message3":"","message4":"","messageType":1,"minTurns":1,"motion":0,"name":"","note":"","overlay":0,"priority":50,"removeAtBattleEnd":false,"removeByDamage":false,"removeByRestriction":false,"removeByWalking":false,"restriction":0,"stepsToRemove":100},
{"id":45,"autoRemovalTiming":0,"chanceByDamage":100,"traits":[],"iconIndex":0,"maxTurns":1,"message1":"","message2":"","message3":"","message4":"","messageType":1,"minTurns":1,"motion":0,"name":"","note":"","overlay":0,"priority":50,"removeAtBattleEnd":false,"removeByDamage":false,"removeByRestriction":false,"removeByWalking":false,"restriction":0,"stepsToRemove":100},
{"id":46,"autoRemovalTiming":0,"chanceByDamage":100,"traits":[],"iconIndex":0,"maxTurns":1,"message1":"","message2":"","message3":"","message4":"","messageType":1,"minTurns":1,"motion":0,"name":"","note":"","overlay":0,"priority":50,"removeAtBattleEnd":false,"removeByDamage":false,"removeByRestriction":false,"removeByWalking":false,"restriction":0,"stepsToRemove":100},
{"id":47,"autoRemovalTiming":0,"chanceByDamage":100,"traits":[],"iconIndex":0,"maxTurns":1,"message1":"","message2":"","message3":"","message4":"","messageType":1,"minTurns":1,"motion":0,"name":"","note":"","overlay":0,"priority":50,"removeAtBattleEnd":false,"removeByDamage":false,"removeByRestriction":false,"removeByWalking":false,"restriction":0,"stepsToRemove":100},
{"id":48,"autoRemovalTiming":0,"chanceByDamage":100,"traits":[],"iconIndex":0,"maxTurns":1,"message1":"","message2":"","message3":"","message4":"","messageType":1,"minTurns":1,"motion":0,"name":"","note":"","overlay":0,"priority":50,"removeAtBattleEnd":false,"removeByDamage":false,"removeByRestriction":false,"removeByWalking":false,"restriction":0,"stepsToRemove":100},
{"id":49,"autoRemovalTiming":0,"chanceByDamage":100,"traits":[],"iconIndex":0,"maxTurns":1,"message1":"","message2":"","message3":"","message4":"","messageType":1,"minTurns":1,"motion":0,"name":"","note":"","overlay":0,"priority":50,"removeAtBattleEnd":false,"removeByDamage":false,"removeByRestriction":false,"removeByWalking":false,"restriction":0,"stepsToRemove":100},
{"id":50,"autoRemovalTiming":0,"chanceByDamage":100,"traits":[],"iconIndex":0,"maxTurns":1,"message1":"","message2":"","message3":"","message4":"","messageType":1,"minTurns":1,"motion":0,"name":"","note":"","overlay":0,"priority":50,"removeAtBattleEnd":false,"removeByDamage":false,"removeByRestriction":false,"removeByWalking":false,"restriction":0,"stepsToRemove":100}
]